AIBridge/__init__.py
AIBridge/exceptions.py
AIBridge/setconfig.py
AIBridge/ai_services/__init__.py
AIBridge/ai_services/ai21labs_text.py
AIBridge/ai_services/ai_abstraction.py
AIBridge/ai_services/ai_services_response.py
AIBridge/ai_services/anthropic_ai.py
AIBridge/ai_services/cohere_llm.py
AIBridge/ai_services/geminin_services.py
AIBridge/ai_services/image_optimisaton.py
AIBridge/ai_services/ollama_services.py
AIBridge/ai_services/openai_images.py
AIBridge/ai_services/openai_services.py
AIBridge/ai_services/process_mq.py
AIBridge/ai_services/stable_diffusion_image.py
AIBridge/constant/__init__.py
AIBridge/constant/common.py
AIBridge/constant/constant.py
AIBridge/database/__init__.py
AIBridge/database/db_layer.py
AIBridge/database/no_sql_service.py
AIBridge/database/session.py
AIBridge/database/sql_service.py
AIBridge/database/table_oprations.py
AIBridge/database/models/__init__.py
AIBridge/database/models/ai_response.py
AIBridge/database/models/prompts.py
AIBridge/database/models/variables.py
AIBridge/output_validation/__init__.py
AIBridge/output_validation/active_validator.py
AIBridge/output_validation/convertors.py
AIBridge/output_validation/validations.py
AIBridge/prompts/__init__.py
AIBridge/prompts/prompt_completion.py
AIBridge/prompts/prompts_save.py
AIBridge/prompts/prompts_varibales.py
AIBridge/queue_integration/__init__.py
AIBridge/queue_integration/assign_queue.py
AIBridge/queue_integration/message_queue.py
AIBridge/queue_integration/queue_model.py
AIBridge/queue_integration/response_class.py
aibridge_test-0.7.1.dist-info/LICENSE
aibridge_test-0.7.1.dist-info/METADATA
aibridge_test-0.7.1.dist-info/WHEEL
aibridge_test-0.7.1.dist-info/top_level.txt
aibridge_test-0.7.1.dist-info/RECORD
