Metadata-Version: 2.2
Name: aibridge_test
Version: 0.7.1
Summary: Bridge for LLM"s
Home-page: https://github.com/me/myproject
Author: Ashish Tilekar
Author-email: ashish.tilekar@opsfuse.com
License: MIT
Classifier: License :: OSI Approved :: MIT License
Classifier: Programming Language :: Python
Classifier: Programming Language :: Python :: 3
Classifier: Programming Language :: Python :: 3.9
Classifier: Programming Language :: Python :: Implementation :: CPython
Classifier: Programming Language :: Python :: Implementation :: PyPy
Requires-Python: >=3.9.0
License-File: LICENSE
Requires-Dist: openai<=1.55.0
Requires-Dist: SQLAlchemy>=2.0.19
Requires-Dist: redis>=4.6.0
Requires-Dist: PyYAML>=6.0.1
Requires-Dist: Jinja2>=3.1.2
Requires-Dist: pymongo>=4.4.1
Requires-Dist: sqlparse>=0.4.4
Requires-Dist: jsonschema>=4.18.4
Requires-Dist: Pillow>=10.0.0
Requires-Dist: google-genai>=1.2.0
Requires-Dist: cohere>=5.13.11
Requires-Dist: ai21>=2.13.0
Requires-Dist: xmltodict>=0.13.0
Requires-Dist: anthropic>=0.45.2
Requires-Dist: ollama<=1.2.2
Dynamic: author
Dynamic: author-email
Dynamic: classifier
Dynamic: description
Dynamic: description-content-type
Dynamic: home-page
Dynamic: license
Dynamic: requires-dist
Dynamic: requires-python
Dynamic: summary
